puffins/__init__.py
puffins/calculus.py
puffins/constants.py
puffins/dates.py
puffins/dynamics.py
puffins/eofs.py
puffins/eq_area.py
puffins/fixed_temp_tropo.py
puffins/grad_bal.py
puffins/had_cell.py
puffins/held_hou_1980.py
puffins/hides.py
puffins/interp.py
puffins/kuo_el.py
puffins/lindzen_hou_1988.py
puffins/names.py
puffins/nb_utils.py
puffins/num_solver.py
puffins/plotting.py
puffins/plumb_hou_1992.py
puffins/stats.py
puffins/thermodynamics.py
puffins/tropopause.py
puffins-0.1.1.data/scripts/set_proj_puff_branch.py
puffins-0.1.1.dist-info/LICENSE
puffins-0.1.1.dist-info/METADATA
puffins-0.1.1.dist-info/WHEEL
puffins-0.1.1.dist-info/top_level.txt
puffins-0.1.1.dist-info/RECORD
