Metadata-Version: 2.1
Name: puffins
Version: 0.1.1
Summary: Functions for computing things in climate science
Home-page: https://github.com/spencerahill/puffins
Author: Spencer A. Hill
Author-email: shill@ldeo.columbia.edu
License: Apache
Keywords: climate science
Platform: UNKNOWN
Classifier: Development Status :: 2 - Pre-Alpha
Classifier: Intended Audience :: Science/Research
Classifier: License :: OSI Approved :: Apache Software License
Classifier: Natural Language :: English
Classifier: Programming Language :: Python :: 3
Classifier: Topic :: Scientific/Engineering :: Atmospheric Science
Requires-Dist: eofs
Requires-Dist: faceted
Requires-Dist: gitpython
Requires-Dist: ipython
Requires-Dist: matplotlib
Requires-Dist: numpy
Requires-Dist: scipy
Requires-Dist: scikit-learn
Requires-Dist: xarray
